binarysearchtree/__init__.py
binarysearchtree/src.py
binarysearchtree/tests.py
binarysearchtree-0.2.0.dist-info/LICENSE
binarysearchtree-0.2.0.dist-info/WHEEL
binarysearchtree-0.2.0.dist-info/METADATA
binarysearchtree-0.2.0.dist-info/RECORD
