Metadata-Version: 2.1
Name: binarysearchtree
Version: 0.2.0
Summary: Binary search tree
Author: Anes Foufa
Author-email: anes.foufa@upply.com
Requires-Python: >=3.7,<4.0
Classifier: Programming Language :: Python :: 3
Classifier: Programming Language :: Python :: 3.7
